[
    {
        "ThickNess": 160.0,
        "WhOpenings": [],
        "WhCurve": {
            "CurvePoint": [
                {
                    "X": 15980.000339562735,
                    "Y": -44.99124587374591,
                    "Z": 29275.000000000789
                },
                {
                    "X": 15980.00033956273,
                    "Y": -1599.9912458737463,
                    "Z": 29275.000000000789
                }
            ]
        },
        "LevelBot": "29500",
        "LevelTop": "29500",
        "Name": "B12-U3/3-W10",
        "Height": 2985.0,
        "Recess": []
    },
    {
        "ThickNess": 90.0,
        "WhOpenings": [],
        "WhCurve": {
            "CurvePoint": [
                {
                    "X": 15980.000339562737,
                    "Y": -44.99124587374591,
                    "Z": 29465.000000000797
                },
                {
                    "X": 18705.000331962696,
                    "Y": -44.991245873754728,
                    "Z": 29465.000000000797
                }
            ]
        },
        "LevelBot": "29500",
        "LevelTop": "32500",
        "Name": null,
        "Height": 2725.0,
        "Recess": []
    },
    {
        "ThickNess": 90.0,
        "WhOpenings": [],
        "WhCurve": {
            "CurvePoint": [
                {
                    "X": 18705.000331962692,
                    "Y": 0.0087541262453590275,
                    "Z": 29275.000000000797
                },
                {
                    "X": 18705.000331962689,
                    "Y": -764.99124587375456,
                    "Z": 29275.000000000797
                }
            ]
        },
        "LevelBot": "29500",
        "LevelTop": "29500",
        "Name": "B12-U3/3-W9",
        "Height": 2985.0,
        "Recess": []
    },
    {
        "ThickNess": 90.0,
        "WhOpenings": [],
        "WhCurve": {
            "CurvePoint": [
                {
                    "X": 18705.000331962692,
                    "Y": -1619.9912458737545,
                    "Z": 29275.000000000797
                },
                {
                    "X": 18705.000331962689,
                    "Y": -2579.9912458737545,
                    "Z": 29275.000000000797
                }
            ]
        },
        "LevelBot": "29500",
        "LevelTop": "29500",
        "Name": "B12-U3/3-W8",
        "Height": 2985.0,
        "Recess": []
    },
    {
        "ThickNess": 90.0,
        "WhOpenings": [],
        "WhCurve": {
            "CurvePoint": [
                {
                    "X": 18705.000339562735,
                    "Y": -5200.00824815291,
                    "Z": 29275.000000000797
                },
                {
                    "X": 18705.000339562732,
                    "Y": -7000.00824815291,
                    "Z": 29275.000000000797
                }
            ]
        },
        "LevelBot": "29500",
        "LevelTop": "29500",
        "Name": null,
        "Height": 2985.0,
        "Recess": []
    },
    {
        "ThickNess": 90.0,
        "WhOpenings": [],
        "WhCurve": {
            "CurvePoint": [
                {
                    "X": 18705.000339562735,
                    "Y": -3534.9912458737549,
                    "Z": 29275.000000000797
                },
                {
                    "X": 18705.000339562735,
                    "Y": -5200.00824815291,
                    "Z": 29275.000000000797
                }
            ]
        },
        "LevelBot": "29500",
        "LevelTop": "32500",
        "Name": "B12-U3/3-W6",
        "Height": 2915.0,
        "Recess": []
    },
    {
        "ThickNess": 160.0,
        "WhOpenings": [],
        "WhCurve": {
            "CurvePoint": [
                {
                    "X": 15980.00033956273,
                    "Y": -1599.9912458737463,
                    "Z": 29465.000000000793
                },
                {
                    "X": 15980.000339562728,
                    "Y": -2399.9912458737463,
                    "Z": 29465.000000000793
                }
            ]
        },
        "LevelBot": "29500",
        "LevelTop": "32500",
        "Name": null,
        "Height": 2725.0,
        "Recess": []
    },
    {
        "ThickNess": 160.0,
        "WhOpenings": [],
        "WhCurve": {
            "CurvePoint": [
                {
                    "X": 15980.000339562728,
                    "Y": -2399.9912458737463,
                    "Z": 29275.000000000789
                },
                {
                    "X": 15980.000339562717,
                    "Y": -5650.0082481529025,
                    "Z": 29275.000000000789
                }
            ]
        },
        "LevelBot": "29500",
        "LevelTop": "29500",
        "Name": null,
        "Height": 2985.0,
        "Recess": []
    }
]